[
  {
    "global_step": 100,
    "epoch": 0,
    "reconstruction_loss": 0.13047197461128235,
    "l1_loss": 0.3402163088321686,
    "total_loss": 0.14067846536636353,
    "alive_count": 1024,
    "alive_frac": 1.0,
    "dead_count": 0,
    "mean_sparsity": 0.480751633644104,
    "mean_activation": 0.40763824462890624,
    "L0": 492.2896875
  },
  {
    "global_step": 200,
    "epoch": 0,
    "reconstruction_loss": 0.08612237870693207,
    "l1_loss": 0.2847522497177124,
    "total_loss": 0.09466494619846344,
    "alive_count": 1024,
    "alive_frac": 1.0,
    "dead_count": 0,
    "mean_sparsity": 0.4737728238105774,
    "mean_activation": 0.358290901184082,
    "L0": 485.143359375
  },
  {
    "global_step": 300,
    "epoch": 0,
    "reconstruction_loss": 0.060817889869213104,
    "l1_loss": 0.25181758403778076,
    "total_loss": 0.06837241351604462,
    "alive_count": 1024,
    "alive_frac": 1.0,
    "dead_count": 0,
    "mean_sparsity": 0.470661997795105,
    "mean_activation": 0.3278303782145182,
    "L0": 481.9579166666667
  },
  {
    "global_step": 400,
    "epoch": 1,
    "reconstruction_loss": 0.048373255878686905,
    "l1_loss": 0.23079489171504974,
    "total_loss": 0.05529710277915001,
    "alive_count": 1024,
    "alive_frac": 1.0,
    "dead_count": 0,
    "mean_sparsity": 0.46911633014678955,
    "mean_activation": 0.306191387912233,
    "L0": 480.3750880212816
  },
  {
    "global_step": 500,
    "epoch": 1,
    "reconstruction_loss": 0.04042555391788483,
    "l1_loss": 0.21663567423820496,
    "total_loss": 0.04692462459206581,
    "alive_count": 1024,
    "alive_frac": 1.0,
    "dead_count": 0,
    "mean_sparsity": 0.46850597858428955,
    "mean_activation": 0.28955301168184094,
    "L0": 479.75014079219073
  },
  {
    "global_step": 600,
    "epoch": 1,
    "reconstruction_loss": 0.03325359895825386,
    "l1_loss": 0.2048194706439972,
    "total_loss": 0.039398182183504105,
    "alive_count": 1024,
    "alive_frac": 1.0,
    "dead_count": 0,
    "mean_sparsity": 0.4686843752861023,
    "mean_activation": 0.27632139124491684,
    "L0": 479.9327980814347
  },
  {
    "global_step": 700,
    "epoch": 2,
    "reconstruction_loss": 0.028184181079268456,
    "l1_loss": 0.19565171003341675,
    "total_loss": 0.034053731709718704,
    "alive_count": 1024,
    "alive_frac": 1.0,
    "dead_count": 0,
    "mean_sparsity": 0.4695487916469574,
    "mean_activation": 0.2655654551038033,
    "L0": 480.8179500939093
  },
  {
    "global_step": 800,
    "epoch": 2,
    "reconstruction_loss": 0.025023512542247772,
    "l1_loss": 0.1919611692428589,
    "total_loss": 0.030782347545027733,
    "alive_count": 1024,
    "alive_frac": 1.0,
    "dead_count": 0,
    "mean_sparsity": 0.47109246253967285,
    "mean_activation": 0.25656820610183084,
    "L0": 482.3986777247477
  },
  {
    "global_step": 900,
    "epoch": 2,
    "reconstruction_loss": 0.022037625312805176,
    "l1_loss": 0.18890002369880676,
    "total_loss": 0.027704626321792603,
    "alive_count": 1024,
    "alive_frac": 1.0,
    "dead_count": 0,
    "mean_sparsity": 0.4733784794807434,
    "mean_activation": 0.24908265191485293,
    "L0": 484.7395174188165
  },
  {
    "global_step": 1000,
    "epoch": 3,
    "reconstruction_loss": 0.018806863576173782,
    "l1_loss": 0.18597596883773804,
    "total_loss": 0.024386141449213028,
    "alive_count": 1024,
    "alive_frac": 1.0,
    "dead_count": 0,
    "mean_sparsity": 0.4764663577079773,
    "mean_activation": 0.24290241174220487,
    "L0": 487.9015433741352
  },
  {
    "global_step": 1100,
    "epoch": 3,
    "reconstruction_loss": 0.01638937182724476,
    "l1_loss": 0.18675243854522705,
    "total_loss": 0.021991945803165436,
    "alive_count": 1024,
    "alive_frac": 1.0,
    "dead_count": 0,
    "mean_sparsity": 0.4804750084877014,
    "mean_activation": 0.2378296909235125,
    "L0": 492.00637395782945
  },
  {
    "global_step": 1200,
    "epoch": 3,
    "reconstruction_loss": 0.01454806700348854,
    "l1_loss": 0.19112202525138855,
    "total_loss": 0.020281728357076645,
    "alive_count": 1024,
    "alive_frac": 1.0,
    "dead_count": 0,
    "mean_sparsity": 0.48536887764930725,
    "mean_activation": 0.23377757083268133,
    "L0": 497.01776073859634
  },
  {
    "global_step": 1300,
    "epoch": 4,
    "reconstruction_loss": 0.012505510821938515,
    "l1_loss": 0.19461464881896973,
    "total_loss": 0.01834394969046116,
    "alive_count": 1024,
    "alive_frac": 1.0,
    "dead_count": 0,
    "mean_sparsity": 0.4909704327583313,
    "mean_activation": 0.23064612294998074,
    "L0": 502.75378094595897
  },
  {
    "global_step": 1400,
    "epoch": 4,
    "reconstruction_loss": 0.011137692257761955,
    "l1_loss": 0.2001815140247345,
    "total_loss": 0.017143137753009796,
    "alive_count": 1024,
    "alive_frac": 1.0,
    "dead_count": 0,
    "mean_sparsity": 0.49708306789398193,
    "mean_activation": 0.22822351219423576,
    "L0": 509.01305786602273
  },
  {
    "global_step": 1500,
    "epoch": 4,
    "reconstruction_loss": 0.009414918720722198,
    "l1_loss": 0.20041829347610474,
    "total_loss": 0.015427467413246632,
    "alive_count": 1024,
    "alive_frac": 1.0,
    "dead_count": 0,
    "mean_sparsity": 0.5033504962921143,
    "mean_activation": 0.22635375477318254,
    "L0": 515.43093230949
  },
  {
    "global_step": 1600,
    "epoch": 5,
    "reconstruction_loss": 0.008434511721134186,
    "l1_loss": 0.20442664623260498,
    "total_loss": 0.01456731092184782,
    "alive_count": 1024,
    "alive_frac": 1.0,
    "dead_count": 0,
    "mean_sparsity": 0.604809045791626,
    "mean_activation": 0.2030890146891276,
    "L0": 619.3244140625
  },
  {
    "global_step": 1700,
    "epoch": 5,
    "reconstruction_loss": 0.0076995426788926125,
    "l1_loss": 0.20558814704418182,
    "total_loss": 0.01386718638241291,
    "alive_count": 1024,
    "alive_frac": 1.0,
    "dead_count": 0,
    "mean_sparsity": 0.6076254844665527,
    "mean_activation": 0.2032148609990659,
    "L0": 622.2085597826087
  },
  {
    "global_step": 1800,
    "epoch": 5,
    "reconstruction_loss": 0.006726850755512714,
    "l1_loss": 0.20288275182247162,
    "total_loss": 0.012813333421945572,
    "alive_count": 1024,
    "alive_frac": 1.0,
    "dead_count": 0,
    "mean_sparsity": 0.6096946001052856,
    "mean_activation": 0.20327607975449674,
    "L0": 624.3272529069767
  },
  {
    "global_step": 1900,
    "epoch": 5,
    "reconstruction_loss": 0.006058546714484692,
    "l1_loss": 0.20006230473518372,
    "total_loss": 0.012060415931046009,
    "alive_count": 1024,
    "alive_frac": 1.0,
    "dead_count": 0,
    "mean_sparsity": 0.6110972166061401,
    "mean_activation": 0.20296819777715774,
    "L0": 625.7634920634921
  },
  {
    "global_step": 2000,
    "epoch": 6,
    "reconstruction_loss": 0.005553736351430416,
    "l1_loss": 0.20184174180030823,
    "total_loss": 0.011608988046646118,
    "alive_count": 1024,
    "alive_frac": 1.0,
    "dead_count": 0,
    "mean_sparsity": 0.6119977235794067,
    "mean_activation": 0.20245035003369843,
    "L0": 626.6856948948043
  },
  {
    "global_step": 2100,
    "epoch": 6,
    "reconstruction_loss": 0.005154500715434551,
    "l1_loss": 0.19797484576702118,
    "total_loss": 0.011093745939433575,
    "alive_count": 1024,
    "alive_frac": 1.0,
    "dead_count": 0,
    "mean_sparsity": 0.6125224232673645,
    "mean_activation": 0.2017456151091975,
    "L0": 627.2229512180305
  },
  {
    "global_step": 2200,
    "epoch": 6,
    "reconstruction_loss": 0.004708560649305582,
    "l1_loss": 0.1968408077955246,
    "total_loss": 0.010613784193992615,
    "alive_count": 1024,
    "alive_frac": 1.0,
    "dead_count": 0,
    "mean_sparsity": 0.612772524356842,
    "mean_activation": 0.20089937278670336,
    "L0": 627.4791211026906
  },
  {
    "global_step": 2300,
    "epoch": 7,
    "reconstruction_loss": 0.0042307088151574135,
    "l1_loss": 0.1891239732503891,
    "total_loss": 0.009904427453875542,
    "alive_count": 1024,
    "alive_frac": 1.0,
    "dead_count": 0,
    "mean_sparsity": 0.6128314733505249,
    "mean_activation": 0.20002543371995665,
    "L0": 627.5394448822345
  },
  {
    "global_step": 2400,
    "epoch": 7,
    "reconstruction_loss": 0.004106431268155575,
    "l1_loss": 0.189976766705513,
    "total_loss": 0.009805734269320965,
    "alive_count": 1024,
    "alive_frac": 1.0,
    "dead_count": 0,
    "mean_sparsity": 0.6127109527587891,
    "mean_activation": 0.1990038027513248,
    "L0": 627.415981875432
  },
  {
    "global_step": 2500,
    "epoch": 7,
    "reconstruction_loss": 0.0038532684557139874,
    "l1_loss": 0.18777534365653992,
    "total_loss": 0.009486528113484383,
    "alive_count": 1024,
    "alive_frac": 1.0,
    "dead_count": 0,
    "mean_sparsity": 0.6124894022941589,
    "mean_activation": 0.19795286224116854,
    "L0": 627.1892483414267
  },
  {
    "global_step": 2600,
    "epoch": 8,
    "reconstruction_loss": 0.0035914378240704536,
    "l1_loss": 0.18417420983314514,
    "total_loss": 0.00911666452884674,
    "alive_count": 1024,
    "alive_frac": 1.0,
    "dead_count": 0,
    "mean_sparsity": 0.6121652126312256,
    "mean_activation": 0.19685771746715294,
    "L0": 626.8572309780094
  },
  {
    "global_step": 2700,
    "epoch": 8,
    "reconstruction_loss": 0.0033704624511301517,
    "l1_loss": 0.1822699010372162,
    "total_loss": 0.008838559500873089,
    "alive_count": 1024,
    "alive_frac": 1.0,
    "dead_count": 0,
    "mean_sparsity": 0.6117908358573914,
    "mean_activation": 0.19573241118361032,
    "L0": 626.4737950200713
  },
  {
    "global_step": 2800,
    "epoch": 8,
    "reconstruction_loss": 0.003316123504191637,
    "l1_loss": 0.17987559735774994,
    "total_loss": 0.00871239136904478,
    "alive_count": 1024,
    "alive_frac": 1.0,
    "dead_count": 0,
    "mean_sparsity": 0.6113802194595337,
    "mean_activation": 0.19459100134746155,
    "L0": 626.0534219406022
  },
  {
    "global_step": 2900,
    "epoch": 9,
    "reconstruction_loss": 0.0031108446419239044,
    "l1_loss": 0.17888805270195007,
    "total_loss": 0.008477486670017242,
    "alive_count": 1024,
    "alive_frac": 1.0,
    "dead_count": 0,
    "mean_sparsity": 0.6109369397163391,
    "mean_activation": 0.19343728331676746,
    "L0": 625.5993714884297
  },
  {
    "global_step": 3000,
    "epoch": 9,
    "reconstruction_loss": 0.0030032219365239143,
    "l1_loss": 0.17632734775543213,
    "total_loss": 0.008293041959404945,
    "alive_count": 1024,
    "alive_frac": 1.0,
    "dead_count": 0,
    "mean_sparsity": 0.6104701161384583,
    "mean_activation": 0.19227630747555527,
    "L0": 625.1214051853818
  },
  {
    "global_step": 3100,
    "epoch": 9,
    "reconstruction_loss": 0.002847536001354456,
    "l1_loss": 0.17390307784080505,
    "total_loss": 0.008064627647399902,
    "alive_count": 1024,
    "alive_frac": 1.0,
    "dead_count": 0,
    "mean_sparsity": 0.6100031137466431,
    "mean_activation": 0.19113533682650194,
    "L0": 624.643087348153
  },
  {
    "global_step": 3200,
    "epoch": 10,
    "reconstruction_loss": 0.002713101916015148,
    "l1_loss": 0.1717909872531891,
    "total_loss": 0.007866831496357918,
    "alive_count": 1024,
    "alive_frac": 1.0,
    "dead_count": 0,
    "mean_sparsity": 0.6018002033233643,
    "mean_activation": 0.17220600446065268,
    "L0": 616.2434244791667
  },
  {
    "global_step": 3300,
    "epoch": 10,
    "reconstruction_loss": 0.002646910957992077,
    "l1_loss": 0.17184880375862122,
    "total_loss": 0.007802375126630068,
    "alive_count": 1024,
    "alive_frac": 1.0,
    "dead_count": 0,
    "mean_sparsity": 0.6014617681503296,
    "mean_activation": 0.17104803232046273,
    "L0": 615.896875
  },
  {
    "global_step": 3400,
    "epoch": 10,
    "reconstruction_loss": 0.0025234974455088377,
    "l1_loss": 0.16755665838718414,
    "total_loss": 0.007550196722149849,
    "alive_count": 1024,
    "alive_frac": 1.0,
    "dead_count": 0,
    "mean_sparsity": 0.6009905338287354,
    "mean_activation": 0.17000410660453466,
    "L0": 615.414402173913
  },
  {
    "global_step": 3500,
    "epoch": 11,
    "reconstruction_loss": 0.0024650178384035826,
    "l1_loss": 0.1653245985507965,
    "total_loss": 0.0074247559532523155,
    "alive_count": 1024,
    "alive_frac": 1.0,
    "dead_count": 0,
    "mean_sparsity": 0.6005591154098511,
    "mean_activation": 0.1690007600530073,
    "L0": 614.9725358125415
  },
  {
    "global_step": 3600,
    "epoch": 11,
    "reconstruction_loss": 0.0022899992763996124,
    "l1_loss": 0.16115817427635193,
    "total_loss": 0.007124744355678558,
    "alive_count": 1024,
    "alive_frac": 1.0,
    "dead_count": 0,
    "mean_sparsity": 0.6001363396644592,
    "mean_activation": 0.1680579596701932,
    "L0": 614.5396259369769
  },
  {
    "global_step": 3700,
    "epoch": 11,
    "reconstruction_loss": 0.002301035914570093,
    "l1_loss": 0.16440226137638092,
    "total_loss": 0.007233103737235069,
    "alive_count": 1024,
    "alive_frac": 1.0,
    "dead_count": 0,
    "mean_sparsity": 0.5997000932693481,
    "mean_activation": 0.16713067940757628,
    "L0": 614.0929106900419
  },
  {
    "global_step": 3800,
    "epoch": 11,
    "reconstruction_loss": 0.0021723583340644836,
    "l1_loss": 0.16043098270893097,
    "total_loss": 0.006985287647694349,
    "alive_count": 1024,
    "alive_frac": 1.0,
    "dead_count": 0,
    "mean_sparsity": 0.5992966294288635,
    "mean_activation": 0.16624871074937317,
    "L0": 613.6797577081575
  },
  {
    "global_step": 3900,
    "epoch": 12,
    "reconstruction_loss": 0.002176393521949649,
    "l1_loss": 0.15964163839817047,
    "total_loss": 0.006965642794966698,
    "alive_count": 1024,
    "alive_frac": 1.0,
    "dead_count": 0,
    "mean_sparsity": 0.5989081859588623,
    "mean_activation": 0.16536177784120143,
    "L0": 613.282008404082
  },
  {
    "global_step": 4000,
    "epoch": 12,
    "reconstruction_loss": 0.002093045972287655,
    "l1_loss": 0.15775690972805023,
    "total_loss": 0.0068257530219852924,
    "alive_count": 1024,
    "alive_frac": 1.0,
    "dead_count": 0,
    "mean_sparsity": 0.598531186580658,
    "mean_activation": 0.16450085218167937,
    "L0": 612.8959354498153
  },
  {
    "global_step": 4100,
    "epoch": 12,
    "reconstruction_loss": 0.002053111093118787,
    "l1_loss": 0.15681451559066772,
    "total_loss": 0.006757546216249466,
    "alive_count": 1024,
    "alive_frac": 1.0,
    "dead_count": 0,
    "mean_sparsity": 0.5981879234313965,
    "mean_activation": 0.16371461480553126,
    "L0": 612.5443779018908
  },
  {
    "global_step": 4200,
    "epoch": 13,
    "reconstruction_loss": 0.0019902491476386786,
    "l1_loss": 0.15347664058208466,
    "total_loss": 0.006594548001885414,
    "alive_count": 1024,
    "alive_frac": 1.0,
    "dead_count": 0,
    "mean_sparsity": 0.5978540182113647,
    "mean_activation": 0.16292216301515058,
    "L0": 612.2025347232775
  },
  {
    "global_step": 4300,
    "epoch": 13,
    "reconstruction_loss": 0.001915384316816926,
    "l1_loss": 0.15301087498664856,
    "total_loss": 0.006505710072815418,
    "alive_count": 1024,
    "alive_frac": 1.0,
    "dead_count": 0,
    "mean_sparsity": 0.5975111722946167,
    "mean_activation": 0.1621315554628424,
    "L0": 611.8514250893278
  },
  {
    "global_step": 4400,
    "epoch": 13,
    "reconstruction_loss": 0.0018666479736566544,
    "l1_loss": 0.15185058116912842,
    "total_loss": 0.0064221653155982494,
    "alive_count": 1024,
    "alive_frac": 1.0,
    "dead_count": 0,
    "mean_sparsity": 0.5972034931182861,
    "mean_activation": 0.16138487311321656,
    "L0": 611.536320382668
  },
  {
    "global_step": 4500,
    "epoch": 14,
    "reconstruction_loss": 0.0018393388018012047,
    "l1_loss": 0.15157106518745422,
    "total_loss": 0.006386470515280962,
    "alive_count": 1024,
    "alive_frac": 1.0,
    "dead_count": 0,
    "mean_sparsity": 0.5969010591506958,
    "mean_activation": 0.16065556481557763,
    "L0": 611.2266735712268
  },
  {
    "global_step": 4600,
    "epoch": 14,
    "reconstruction_loss": 0.0018109837546944618,
    "l1_loss": 0.1508214771747589,
    "total_loss": 0.006335627753287554,
    "alive_count": 1024,
    "alive_frac": 1.0,
    "dead_count": 0,
    "mean_sparsity": 0.596592903137207,
    "mean_activation": 0.1599140118805271,
    "L0": 610.911084843709
  },
  {
    "global_step": 4700,
    "epoch": 14,
    "reconstruction_loss": 0.001760579994879663,
    "l1_loss": 0.1501605212688446,
    "total_loss": 0.006265395786613226,
    "alive_count": 1024,
    "alive_frac": 1.0,
    "dead_count": 0,
    "mean_sparsity": 0.5962979793548584,
    "mean_activation": 0.15921310925481752,
    "L0": 610.6091154570003
  },
  {
    "global_step": 4800,
    "epoch": 15,
    "reconstruction_loss": 0.001753863412886858,
    "l1_loss": 0.14748337864875793,
    "total_loss": 0.006178364623337984,
    "alive_count": 1024,
    "alive_frac": 1.0,
    "dead_count": 0,
    "mean_sparsity": 0.591411828994751,
    "mean_activation": 0.1474757406446669,
    "L0": 605.6057291666667
  },
  {
    "global_step": 4900,
    "epoch": 15,
    "reconstruction_loss": 0.001685157185420394,
    "l1_loss": 0.14623123407363892,
    "total_loss": 0.006072093732655048,
    "alive_count": 1024,
    "alive_frac": 1.0,
    "dead_count": 0,
    "mean_sparsity": 0.591194748878479,
    "mean_activation": 0.1469878624225485,
    "L0": 605.3834590517241
  },
  {
    "global_step": 5000,
    "epoch": 15,
    "reconstruction_loss": 0.0016492808936163783,
    "l1_loss": 0.14404268562793732,
    "total_loss": 0.005970561411231756,
    "alive_count": 1024,
    "alive_frac": 1.0,
    "dead_count": 0,
    "mean_sparsity": 0.591019868850708,
    "mean_activation": 0.14650049014967315,
    "L0": 605.2043367346939
  },
  {
    "global_step": 5100,
    "epoch": 16,
    "reconstruction_loss": 0.0016245002625510097,
    "l1_loss": 0.14354196190834045,
    "total_loss": 0.005930759012699127,
    "alive_count": 1024,
    "alive_frac": 1.0,
    "dead_count": 0,
    "mean_sparsity": 0.5908628702163696,
    "mean_activation": 0.14604004393600853,
    "L0": 605.0435985845205
  },
  {
    "global_step": 5200,
    "epoch": 16,
    "reconstruction_loss": 0.0015806941082701087,
    "l1_loss": 0.1425158828496933,
    "total_loss": 0.0058561707846820354,
    "alive_count": 1024,
    "alive_frac": 1.0,
    "dead_count": 0,
    "mean_sparsity": 0.5906826257705688,
    "mean_activation": 0.14553404461272063,
    "L0": 604.8590113212854
  },
  {
    "global_step": 5300,
    "epoch": 16,
    "reconstruction_loss": 0.0016005546785891056,
    "l1_loss": 0.143492192029953,
    "total_loss": 0.005905320402234793,
    "alive_count": 1024,
    "alive_frac": 1.0,
    "dead_count": 0,
    "mean_sparsity": 0.5904666185379028,
    "mean_activation": 0.14499755705219275,
    "L0": 604.6377360656679
  },
  {
    "global_step": 5400,
    "epoch": 17,
    "reconstruction_loss": 0.0015460727736353874,
    "l1_loss": 0.14262807369232178,
    "total_loss": 0.005824914667755365,
    "alive_count": 1024,
    "alive_frac": 1.0,
    "dead_count": 0,
    "mean_sparsity": 0.5902845859527588,
    "mean_activation": 0.1444964811137875,
    "L0": 604.4514124842249
  },
  {
    "global_step": 5500,
    "epoch": 17,
    "reconstruction_loss": 0.00150597607716918,
    "l1_loss": 0.14048534631729126,
    "total_loss": 0.005720536224544048,
    "alive_count": 1024,
    "alive_frac": 1.0,
    "dead_count": 0,
    "mean_sparsity": 0.5901001691818237,
    "mean_activation": 0.14398083095039282,
    "L0": 604.2625829762205
  },
  {
    "global_step": 5600,
    "epoch": 17,
    "reconstruction_loss": 0.0014726208755746484,
    "l1_loss": 0.13749678432941437,
    "total_loss": 0.005597524344921112,
    "alive_count": 1024,
    "alive_frac": 1.0,
    "dead_count": 0,
    "mean_sparsity": 0.589911937713623,
    "mean_activation": 0.14348568219483743,
    "L0": 604.0697726094363
  },
  {
    "global_step": 5700,
    "epoch": 17,
    "reconstruction_loss": 0.001487873261794448,
    "l1_loss": 0.13925030827522278,
    "total_loss": 0.005665382370352745,
    "alive_count": 1024,
    "alive_frac": 1.0,
    "dead_count": 0,
    "mean_sparsity": 0.5897209644317627,
    "mean_activation": 0.1429949634699275,
    "L0": 603.8742467386265
  },
  {
    "global_step": 5800,
    "epoch": 18,
    "reconstruction_loss": 0.0014000603696331382,
    "l1_loss": 0.13704831898212433,
    "total_loss": 0.00551151018589735,
    "alive_count": 1024,
    "alive_frac": 1.0,
    "dead_count": 0,
    "mean_sparsity": 0.589525580406189,
    "mean_activation": 0.14250701025784082,
    "L0": 603.6742054339035
  },
  {
    "global_step": 5900,
    "epoch": 18,
    "reconstruction_loss": 0.0014718477614223957,
    "l1_loss": 0.1365666687488556,
    "total_loss": 0.0055688475258648396,
    "alive_count": 1024,
    "alive_frac": 1.0,
    "dead_count": 0,
    "mean_sparsity": 0.5893377065658569,
    "mean_activation": 0.14202269389983052,
    "L0": 603.4818358253834
  },
  {
    "global_step": 6000,
    "epoch": 18,
    "reconstruction_loss": 0.001392608741298318,
    "l1_loss": 0.1361694633960724,
    "total_loss": 0.005477692931890488,
    "alive_count": 1024,
    "alive_frac": 1.0,
    "dead_count": 0,
    "mean_sparsity": 0.5891423225402832,
    "mean_activation": 0.14154012078023276,
    "L0": 603.2817032400774
  },
  {
    "global_step": 6100,
    "epoch": 19,
    "reconstruction_loss": 0.0013622450642287731,
    "l1_loss": 0.13354328274726868,
    "total_loss": 0.0053685433231294155,
    "alive_count": 1024,
    "alive_frac": 1.0,
    "dead_count": 0,
    "mean_sparsity": 0.5889666080474854,
    "mean_activation": 0.14106962869713596,
    "L0": 603.101759612699
  },
  {
    "global_step": 6200,
    "epoch": 19,
    "reconstruction_loss": 0.0013868371024727821,
    "l1_loss": 0.1342877745628357,
    "total_loss": 0.005415470339357853,
    "alive_count": 1024,
    "alive_frac": 1.0,
    "dead_count": 0,
    "mean_sparsity": 0.5887829065322876,
    "mean_activation": 0.14058986287339703,
    "L0": 602.913698986223
  },
  {
    "global_step": 6300,
    "epoch": 19,
    "reconstruction_loss": 0.0013545553665608168,
    "l1_loss": 0.13439428806304932,
    "total_loss": 0.005386384204030037,
    "alive_count": 1024,
    "alive_frac": 1.0,
    "dead_count": 0,
    "mean_sparsity": 0.5885924100875854,
    "mean_activation": 0.1401080533447958,
    "L0": 602.7186613726602
  },
  {
    "global_step": 6400,
    "epoch": 20,
    "reconstruction_loss": 0.0013094928581267595,
    "l1_loss": 0.13141566514968872,
    "total_loss": 0.0052519626915454865,
    "alive_count": 1024,
    "alive_frac": 1.0,
    "dead_count": 0,
    "mean_sparsity": 0.5856058597564697,
    "mean_activation": 0.13231183687845866,
    "L0": 599.6603515625
  },
  {
    "global_step": 6500,
    "epoch": 20,
    "reconstruction_loss": 0.001325956778600812,
    "l1_loss": 0.13197660446166992,
    "total_loss": 0.005285254679620266,
    "alive_count": 1024,
    "alive_frac": 1.0,
    "dead_count": 0,
    "mean_sparsity": 0.5853146314620972,
    "mean_activation": 0.1316978931427002,
    "L0": 599.36220703125
  },
  {
    "global_step": 6600,
    "epoch": 20,
    "reconstruction_loss": 0.001301157521083951,
    "l1_loss": 0.12794607877731323,
    "total_loss": 0.005139539949595928,
    "alive_count": 1024,
    "alive_frac": 1.0,
    "dead_count": 0,
    "mean_sparsity": 0.5851052403450012,
    "mean_activation": 0.1312109873845027,
    "L0": 599.1478365384615
  },
  {
    "global_step": 6700,
    "epoch": 21,
    "reconstruction_loss": 0.0013082930818200111,
    "l1_loss": 0.12901976704597473,
    "total_loss": 0.005178886000066996,
    "alive_count": 1024,
    "alive_frac": 1.0,
    "dead_count": 0,
    "mean_sparsity": 0.5849100351333618,
    "mean_activation": 0.13077546161067516,
    "L0": 598.947917572385
  },
  {
    "global_step": 6800,
    "epoch": 21,
    "reconstruction_loss": 0.0012611825950443745,
    "l1_loss": 0.12671485543251038,
    "total_loss": 0.005062628071755171,
    "alive_count": 1024,
    "alive_frac": 1.0,
    "dead_count": 0,
    "mean_sparsity": 0.5847363471984863,
    "mean_activation": 0.13033095444718898,
    "L0": 598.7700156451942
  },
  {
    "global_step": 6900,
    "epoch": 21,
    "reconstruction_loss": 0.0012383059365674853,
    "l1_loss": 0.127497136592865,
    "total_loss": 0.005063219927251339,
    "alive_count": 1024,
    "alive_frac": 1.0,
    "dead_count": 0,
    "mean_sparsity": 0.5845289826393127,
    "mean_activation": 0.1298886497262723,
    "L0": 598.5576783419921
  },
  {
    "global_step": 7000,
    "epoch": 22,
    "reconstruction_loss": 0.0012130237882956862,
    "l1_loss": 0.12651772797107697,
    "total_loss": 0.005008555483072996,
    "alive_count": 1024,
    "alive_frac": 1.0,
    "dead_count": 0,
    "mean_sparsity": 0.5843522548675537,
    "mean_activation": 0.12943267749887344,
    "L0": 598.3767194763305
  },
  {
    "global_step": 7100,
    "epoch": 22,
    "reconstruction_loss": 0.0012207786785438657,
    "l1_loss": 0.12490854412317276,
    "total_loss": 0.004968035034835339,
    "alive_count": 1024,
    "alive_frac": 1.0,
    "dead_count": 0,
    "mean_sparsity": 0.5841376185417175,
    "mean_activation": 0.12897589673871077,
    "L0": 598.156906350383
  },
  {
    "global_step": 7200,
    "epoch": 22,
    "reconstruction_loss": 0.0012111839605495334,
    "l1_loss": 0.12549160420894623,
    "total_loss": 0.0049759321846067905,
    "alive_count": 1024,
    "alive_frac": 1.0,
    "dead_count": 0,
    "mean_sparsity": 0.5839061737060547,
    "mean_activation": 0.12851840736095443,
    "L0": 597.9198748271596
  },
  {
    "global_step": 7300,
    "epoch": 23,
    "reconstruction_loss": 0.0012003888841718435,
    "l1_loss": 0.1247556060552597,
    "total_loss": 0.0049430569633841515,
    "alive_count": 1024,
    "alive_frac": 1.0,
    "dead_count": 0,
    "mean_sparsity": 0.5837075710296631,
    "mean_activation": 0.12808308453490364,
    "L0": 597.7165313243975
  },
  {
    "global_step": 7400,
    "epoch": 23,
    "reconstruction_loss": 0.0011928474996238947,
    "l1_loss": 0.12391339987516403,
    "total_loss": 0.004910249263048172,
    "alive_count": 1024,
    "alive_frac": 1.0,
    "dead_count": 0,
    "mean_sparsity": 0.5834783911705017,
    "mean_activation": 0.12763266403873696,
    "L0": 597.4818533502643
  },
  {
    "global_step": 7500,
    "epoch": 23,
    "reconstruction_loss": 0.0011358987540006638,
    "l1_loss": 0.1193763017654419,
    "total_loss": 0.0047171879559755325,
    "alive_count": 1024,
    "alive_frac": 1.0,
    "dead_count": 0,
    "mean_sparsity": 0.5832730531692505,
    "mean_activation": 0.12719845790444648,
    "L0": 597.2716725575372
  },
  {
    "global_step": 7600,
    "epoch": 23,
    "reconstruction_loss": 0.0011667883954942226,
    "l1_loss": 0.12253062427043915,
    "total_loss": 0.004842706955969334,
    "alive_count": 1024,
    "alive_frac": 1.0,
    "dead_count": 0,
    "mean_sparsity": 0.5830622911453247,
    "mean_activation": 0.1267893095087301,
    "L0": 597.0558080619924
  },
  {
    "global_step": 7700,
    "epoch": 24,
    "reconstruction_loss": 0.001159419072791934,
    "l1_loss": 0.12045688927173615,
    "total_loss": 0.004773125983774662,
    "alive_count": 1024,
    "alive_frac": 1.0,
    "dead_count": 0,
    "mean_sparsity": 0.5828409194946289,
    "mean_activation": 0.12637250145301998,
    "L0": 596.8292054138661
  },
  {
    "global_step": 7800,
    "epoch": 24,
    "reconstruction_loss": 0.001135197002440691,
    "l1_loss": 0.12025666981935501,
    "total_loss": 0.004742897115647793,
    "alive_count": 1024,
    "alive_frac": 1.0,
    "dead_count": 0,
    "mean_sparsity": 0.5826465487480164,
    "mean_activation": 0.12598158726202727,
    "L0": 596.630048880885
  },
  {
    "global_step": 7900,
    "epoch": 24,
    "reconstruction_loss": 0.001084333285689354,
    "l1_loss": 0.11842535436153412,
    "total_loss": 0.004637093748897314,
    "alive_count": 1024,
    "alive_frac": 1.0,
    "dead_count": 0,
    "mean_sparsity": 0.5824435949325562,
    "mean_activation": 0.1255888587235926,
    "L0": 596.4222775058181
  },
  {
    "global_step": 8000,
    "epoch": 25,
    "reconstruction_loss": 0.0010986836859956384,
    "l1_loss": 0.11961235105991364,
    "total_loss": 0.004687054082751274,
    "alive_count": 1024,
    "alive_frac": 1.0,
    "dead_count": 0,
    "mean_sparsity": 0.579113245010376,
    "mean_activation": 0.11925259908040364,
    "L0": 593.0119791666667
  },
  {
    "global_step": 8100,
    "epoch": 25,
    "reconstruction_loss": 0.0010775290429592133,
    "l1_loss": 0.11755851656198502,
    "total_loss": 0.004604284651577473,
    "alive_count": 1024,
    "alive_frac": 1.0,
    "dead_count": 0,
    "mean_sparsity": 0.5788542032241821,
    "mean_activation": 0.11884432111467634,
    "L0": 592.7467410714286
  },
  {
    "global_step": 8200,
    "epoch": 25,
    "reconstruction_loss": 0.001066187396645546,
    "l1_loss": 0.11804509162902832,
    "total_loss": 0.004607540089637041,
    "alive_count": 1024,
    "alive_frac": 1.0,
    "dead_count": 0,
    "mean_sparsity": 0.5786632299423218,
    "mean_activation": 0.1186442704634233,
    "L0": 592.5511363636364
  },
  {
    "global_step": 8300,
    "epoch": 26,
    "reconstruction_loss": 0.0010832524858415127,
    "l1_loss": 0.11816226691007614,
    "total_loss": 0.004628120455890894,
    "alive_count": 1024,
    "alive_frac": 1.0,
    "dead_count": 0,
    "mean_sparsity": 0.5785462260246277,
    "mean_activation": 0.11843581438840664,
    "L0": 592.4313079041816
  },
  {
    "global_step": 8400,
    "epoch": 26,
    "reconstruction_loss": 0.0010615315986797214,
    "l1_loss": 0.11809904873371124,
    "total_loss": 0.00460450304672122,
    "alive_count": 1024,
    "alive_frac": 1.0,
    "dead_count": 0,
    "mean_sparsity": 0.5783554315567017,
    "mean_activation": 0.11820401015249325,
    "L0": 592.2359528357815
  },
  {
    "global_step": 8500,
    "epoch": 26,
    "reconstruction_loss": 0.001050222897902131,
    "l1_loss": 0.11704420298337936,
    "total_loss": 0.004561549052596092,
    "alive_count": 1024,
    "alive_frac": 1.0,
    "dead_count": 0,
    "mean_sparsity": 0.5781935453414917,
    "mean_activation": 0.11792941866771395,
    "L0": 592.0702355693379
  },
  {
    "global_step": 8600,
    "epoch": 27,
    "reconstruction_loss": 0.001027583028189838,
    "l1_loss": 0.11646555364131927,
    "total_loss": 0.004521549679338932,
    "alive_count": 1024,
    "alive_frac": 1.0,
    "dead_count": 0,
    "mean_sparsity": 0.5780398845672607,
    "mean_activation": 0.11770963620170903,
    "L0": 591.9127631945089
  },
  {
    "global_step": 8700,
    "epoch": 27,
    "reconstruction_loss": 0.0010556604247540236,
    "l1_loss": 0.11812125891447067,
    "total_loss": 0.004599298350512981,
    "alive_count": 1024,
    "alive_frac": 1.0,
    "dead_count": 0,
    "mean_sparsity": 0.5779041051864624,
    "mean_activation": 0.11749923727006098,
    "L0": 591.7737662547452
  },
  {
    "global_step": 8800,
    "epoch": 27,
    "reconstruction_loss": 0.001015419838950038,
    "l1_loss": 0.11500509828329086,
    "total_loss": 0.004465572535991669,
    "alive_count": 1024,
    "alive_frac": 1.0,
    "dead_count": 0,
    "mean_sparsity": 0.5777369141578674,
    "mean_activation": 0.11725411873144803,
    "L0": 591.6026035333667
  },
  {
    "global_step": 8900,
    "epoch": 28,
    "reconstruction_loss": 0.000972671085037291,
    "l1_loss": 0.11404138803482056,
    "total_loss": 0.004393912851810455,
    "alive_count": 1024,
    "alive_frac": 1.0,
    "dead_count": 0,
    "mean_sparsity": 0.5776143074035645,
    "mean_activation": 0.11704702683237404,
    "L0": 591.4771216645795
  },
  {
    "global_step": 9000,
    "epoch": 28,
    "reconstruction_loss": 0.0009826581226661801,
    "l1_loss": 0.11351525783538818,
    "total_loss": 0.004388115834444761,
    "alive_count": 1024,
    "alive_frac": 1.0,
    "dead_count": 0,
    "mean_sparsity": 0.5774784088134766,
    "mean_activation": 0.11684573298233993,
    "L0": 591.3379728037737
  },
  {
    "global_step": 9100,
    "epoch": 28,
    "reconstruction_loss": 0.0009785292204469442,
    "l1_loss": 0.11441822350025177,
    "total_loss": 0.004411076195538044,
    "alive_count": 1024,
    "alive_frac": 1.0,
    "dead_count": 0,
    "mean_sparsity": 0.5773530602455139,
    "mean_activation": 0.11663871521072504,
    "L0": 591.2094398423142
  },
  {
    "global_step": 9200,
    "epoch": 29,
    "reconstruction_loss": 0.0009949547238647938,
    "l1_loss": 0.1161181628704071,
    "total_loss": 0.0044784992933273315,
    "alive_count": 1024,
    "alive_frac": 1.0,
    "dead_count": 0,
    "mean_sparsity": 0.5772340297698975,
    "mean_activation": 0.11645776388769521,
    "L0": 591.0876632943719
  },
  {
    "global_step": 9300,
    "epoch": 29,
    "reconstruction_loss": 0.0009801139822229743,
    "l1_loss": 0.11304327100515366,
    "total_loss": 0.004371412098407745,
    "alive_count": 1024,
    "alive_frac": 1.0,
    "dead_count": 0,
    "mean_sparsity": 0.5771079063415527,
    "mean_activation": 0.11626479695397163,
    "L0": 590.9584737273473
  },
  {
    "global_step": 9400,
    "epoch": 29,
    "reconstruction_loss": 0.0009723479161038995,
    "l1_loss": 0.11370377242565155,
    "total_loss": 0.004383461084216833,
    "alive_count": 1024,
    "alive_frac": 1.0,
    "dead_count": 0,
    "mean_sparsity": 0.5770021677017212,
    "mean_activation": 0.11608862887010865,
    "L0": 590.850309820898
  },
  {
    "global_step": 9500,
    "epoch": 29,
    "reconstruction_loss": 0.0009485493646934628,
    "l1_loss": 0.1129724532365799,
    "total_loss": 0.004337722901254892,
    "alive_count": 1024,
    "alive_frac": 1.0,
    "dead_count": 0,
    "mean_sparsity": 0.576885998249054,
    "mean_activation": 0.11590585389488614,
    "L0": 590.7312614259598
  },
  {
    "global_step": 9600,
    "epoch": 30,
    "reconstruction_loss": 0.000940763158723712,
    "l1_loss": 0.1119694709777832,
    "total_loss": 0.004299847409129143,
    "alive_count": 1024,
    "alive_frac": 1.0,
    "dead_count": 0,
    "mean_sparsity": 0.574871301651001,
    "mean_activation": 0.11301614973280165,
    "L0": 588.6681423611111
  },
  {
    "global_step": 9700,
    "epoch": 30,
    "reconstruction_loss": 0.0009334399364888668,
    "l1_loss": 0.11208957433700562,
    "total_loss": 0.004296126775443554,
    "alive_count": 1024,
    "alive_frac": 1.0,
    "dead_count": 0,
    "mean_sparsity": 0.5749863386154175,
    "mean_activation": 0.11294986323306436,
    "L0": 588.785978618421
  },
  {
    "global_step": 9800,
    "epoch": 30,
    "reconstruction_loss": 0.0009476238046772778,
    "l1_loss": 0.1128004714846611,
    "total_loss": 0.004331638105213642,
    "alive_count": 1024,
    "alive_frac": 1.0,
    "dead_count": 0,
    "mean_sparsity": 0.5748716592788696,
    "mean_activation": 0.11273993130387931,
    "L0": 588.6686422413793
  },
  {
    "global_step": 9900,
    "epoch": 31,
    "reconstruction_loss": 0.0009493568795733154,
    "l1_loss": 0.11308050155639648,
    "total_loss": 0.004341771826148033,
    "alive_count": 1024,
    "alive_frac": 1.0,
    "dead_count": 0,
    "mean_sparsity": 0.5748000144958496,
    "mean_activation": 0.11259782866292833,
    "L0": 588.5952170772811
  },
  {
    "global_step": 10000,
    "epoch": 31,
    "reconstruction_loss": 0.0009553113486617804,
    "l1_loss": 0.1127396672964096,
    "total_loss": 0.004337501246482134,
    "alive_count": 1024,
    "alive_frac": 1.0,
    "dead_count": 0,
    "mean_sparsity": 0.574743390083313,
    "mean_activation": 0.11245750727823095,
    "L0": 588.5372581572058
  },
  {
    "global_step": 10100,
    "epoch": 31,
    "reconstruction_loss": 0.0009233640739694238,
    "l1_loss": 0.11148222535848618,
    "total_loss": 0.004267830867320299,
    "alive_count": 1024,
    "alive_frac": 1.0,
    "dead_count": 0,
    "mean_sparsity": 0.5746577382087708,
    "mean_activation": 0.11232134669009464,
    "L0": 588.4494989661206
  },
  {
    "global_step": 10200,
    "epoch": 32,
    "reconstruction_loss": 0.0009223241358995438,
    "l1_loss": 0.11028797924518585,
    "total_loss": 0.004230963531881571,
    "alive_count": 1024,
    "alive_frac": 1.0,
    "dead_count": 0,
    "mean_sparsity": 0.5745801329612732,
    "mean_activation": 0.11220124728146834,
    "L0": 588.3700662371836
  },
  {
    "global_step": 10300,
    "epoch": 32,
    "reconstruction_loss": 0.0009096593130379915,
    "l1_loss": 0.11076506972312927,
    "total_loss": 0.004232611507177353,
    "alive_count": 1024,
    "alive_frac": 1.0,
    "dead_count": 0,
    "mean_sparsity": 0.5744913816452026,
    "mean_activation": 0.1120665531870246,
    "L0": 588.2792171777197
  },
  {
    "global_step": 10400,
    "epoch": 32,
    "reconstruction_loss": 0.0009196468163281679,
    "l1_loss": 0.11191380023956299,
    "total_loss": 0.004277060739696026,
    "alive_count": 1024,
    "alive_frac": 1.0,
    "dead_count": 0,
    "mean_sparsity": 0.5744131803512573,
    "mean_activation": 0.1119454208619735,
    "L0": 588.1991421137755
  },
  {
    "global_step": 10500,
    "epoch": 33,
    "reconstruction_loss": 0.0009129284881055355,
    "l1_loss": 0.11177428811788559,
    "total_loss": 0.004266156814992428,
    "alive_count": 1024,
    "alive_frac": 1.0,
    "dead_count": 0,
    "mean_sparsity": 0.5743120908737183,
    "mean_activation": 0.11182156344373557,
    "L0": 588.0955633557853
  },
  {
    "global_step": 10600,
    "epoch": 33,
    "reconstruction_loss": 0.000899149919860065,
    "l1_loss": 0.10974498093128204,
    "total_loss": 0.004191499203443527,
    "alive_count": 1024,
    "alive_frac": 1.0,
    "dead_count": 0,
    "mean_sparsity": 0.5742228031158447,
    "mean_activation": 0.11170956011023606,
    "L0": 588.0041351980013
  },
  {
    "global_step": 10700,
    "epoch": 33,
    "reconstruction_loss": 0.0008838284411467612,
    "l1_loss": 0.10933306813240051,
    "total_loss": 0.004163820296525955,
    "alive_count": 1024,
    "alive_frac": 1.0,
    "dead_count": 0,
    "mean_sparsity": 0.5741338729858398,
    "mean_activation": 0.11158164651165084,
    "L0": 587.9130000262999
  },
  {
    "global_step": 10800,
    "epoch": 34,
    "reconstruction_loss": 0.0008770741987973452,
    "l1_loss": 0.11009523272514343,
    "total_loss": 0.004179931245744228,
    "alive_count": 1024,
    "alive_frac": 1.0,
    "dead_count": 0,
    "mean_sparsity": 0.5740414261817932,
    "mean_activation": 0.111467378299892,
    "L0": 587.8184642267742
  },
  {
    "global_step": 10900,
    "epoch": 34,
    "reconstruction_loss": 0.0008569450583308935,
    "l1_loss": 0.1089029312133789,
    "total_loss": 0.004124033264815807,
    "alive_count": 1024,
    "alive_frac": 1.0,
    "dead_count": 0,
    "mean_sparsity": 0.5739556550979614,
    "mean_activation": 0.11134904002876993,
    "L0": 587.7306098549681
  },
  {
    "global_step": 11000,
    "epoch": 34,
    "reconstruction_loss": 0.0008416505297645926,
    "l1_loss": 0.10775907337665558,
    "total_loss": 0.004074422642588615,
    "alive_count": 1024,
    "alive_frac": 1.0,
    "dead_count": 0,
    "mean_sparsity": 0.5738667249679565,
    "mean_activation": 0.11123896987385513,
    "L0": 587.6395681035207
  },
  {
    "global_step": 11100,
    "epoch": 35,
    "reconstruction_loss": 0.0008703932981006801,
    "l1_loss": 0.10810789465904236,
    "total_loss": 0.004113629925996065,
    "alive_count": 1024,
    "alive_frac": 1.0,
    "dead_count": 0,
    "mean_sparsity": 0.5717276930809021,
    "mean_activation": 0.10909497737884521,
    "L0": 585.449169921875
  },
  {
    "global_step": 11200,
    "epoch": 35,
    "reconstruction_loss": 0.0008839101064950228,
    "l1_loss": 0.10902128368616104,
    "total_loss": 0.004154548514634371,
    "alive_count": 1024,
    "alive_frac": 1.0,
    "dead_count": 0,
    "mean_sparsity": 0.5721714496612549,
    "mean_activation": 0.10922059558686756,
    "L0": 585.9035714285715
  },
  {
    "global_step": 11300,
    "epoch": 35,
    "reconstruction_loss": 0.000857791630551219,
    "l1_loss": 0.10951699316501617,
    "total_loss": 0.004143301397562027,
    "alive_count": 1024,
    "alive_frac": 1.0,
    "dead_count": 0,
    "mean_sparsity": 0.5720856785774231,
    "mean_activation": 0.10912988244033442,
    "L0": 585.8157393292682
  },
  {
    "global_step": 11400,
    "epoch": 35,
    "reconstruction_loss": 0.0008859065128490329,
    "l1_loss": 0.11133348941802979,
    "total_loss": 0.004225911106914282,
    "alive_count": 1024,
    "alive_frac": 1.0,
    "dead_count": 0,
    "mean_sparsity": 0.5720517039299011,
    "mean_activation": 0.10907844168240907,
    "L0": 585.7809426229509
  },
  {
    "global_step": 11500,
    "epoch": 36,
    "reconstruction_loss": 0.0008704770007170737,
    "l1_loss": 0.10912057012319565,
    "total_loss": 0.004144093953073025,
    "alive_count": 1024,
    "alive_frac": 1.0,
    "dead_count": 0,
    "mean_sparsity": 0.5718938112258911,
    "mean_activation": 0.10896436041155533,
    "L0": 585.6193107178734
  },
  {
    "global_step": 11600,
    "epoch": 36,
    "reconstruction_loss": 0.0008690739050507545,
    "l1_loss": 0.11044059693813324,
    "total_loss": 0.004182291682809591,
    "alive_count": 1024,
    "alive_frac": 1.0,
    "dead_count": 0,
    "mean_sparsity": 0.5717730522155762,
    "mean_activation": 0.10886061214453875,
    "L0": 585.4956322408773
  },
  {
    "global_step": 11700,
    "epoch": 36,
    "reconstruction_loss": 0.0008394434116780758,
    "l1_loss": 0.10720040649175644,
    "total_loss": 0.004055455327033997,
    "alive_count": 1024,
    "alive_frac": 1.0,
    "dead_count": 0,
    "mean_sparsity": 0.5716773271560669,
    "mean_activation": 0.10875733343350913,
    "L0": 585.3975492477122
  },
  {
    "global_step": 11800,
    "epoch": 37,
    "reconstruction_loss": 0.0008534484659321606,
    "l1_loss": 0.1081596240401268,
    "total_loss": 0.0040982370264828205,
    "alive_count": 1024,
    "alive_frac": 1.0,
    "dead_count": 0,
    "mean_sparsity": 0.5715648531913757,
    "mean_activation": 0.10867317971386312,
    "L0": 585.2824349524909
  },
  {
    "global_step": 11900,
    "epoch": 37,
    "reconstruction_loss": 0.0008524114964529872,
    "l1_loss": 0.10787881910800934,
    "total_loss": 0.004088776186108589,
    "alive_count": 1024,
    "alive_frac": 1.0,
    "dead_count": 0,
    "mean_sparsity": 0.5714484453201294,
    "mean_activation": 0.10856391248857981,
    "L0": 585.1632843480289
  },
  {
    "global_step": 12000,
    "epoch": 37,
    "reconstruction_loss": 0.0008341713692061603,
    "l1_loss": 0.10749411582946777,
    "total_loss": 0.004058994818478823,
    "alive_count": 1024,
    "alive_frac": 1.0,
    "dead_count": 0,
    "mean_sparsity": 0.5713444948196411,
    "mean_activation": 0.10847787057106183,
    "L0": 585.0567733904986
  },
  {
    "global_step": 12100,
    "epoch": 38,
    "reconstruction_loss": 0.0008283000206574798,
    "l1_loss": 0.10689975321292877,
    "total_loss": 0.004035292658954859,
    "alive_count": 1024,
    "alive_frac": 1.0,
    "dead_count": 0,
    "mean_sparsity": 0.5712277889251709,
    "mean_activation": 0.10837495351875215,
    "L0": 584.9372332803788
  },
  {
    "global_step": 12200,
    "epoch": 38,
    "reconstruction_loss": 0.0008151569636538625,
    "l1_loss": 0.1059291809797287,
    "total_loss": 0.0039930325001478195,
    "alive_count": 1024,
    "alive_frac": 1.0,
    "dead_count": 0,
    "mean_sparsity": 0.5711109638214111,
    "mean_activation": 0.10828461401341599,
    "L0": 584.817664221171
  },
  {
    "global_step": 12300,
    "epoch": 38,
    "reconstruction_loss": 0.0008159431745298207,
    "l1_loss": 0.10687687247991562,
    "total_loss": 0.004022249486297369,
    "alive_count": 1024,
    "alive_frac": 1.0,
    "dead_count": 0,
    "mean_sparsity": 0.5710071325302124,
    "mean_activation": 0.10819460547311248,
    "L0": 584.7112692517467
  },
  {
    "global_step": 12400,
    "epoch": 39,
    "reconstruction_loss": 0.0008115606033243239,
    "l1_loss": 0.10640305280685425,
    "total_loss": 0.00400365237146616,
    "alive_count": 1024,
    "alive_frac": 1.0,
    "dead_count": 0,
    "mean_sparsity": 0.5708862543106079,
    "mean_activation": 0.10809982734682372,
    "L0": 584.5875635735534
  },
  {
    "global_step": 12500,
    "epoch": 39,
    "reconstruction_loss": 0.0008342003566212952,
    "l1_loss": 0.10626088082790375,
    "total_loss": 0.004022026900202036,
    "alive_count": 1024,
    "alive_frac": 1.0,
    "dead_count": 0,
    "mean_sparsity": 0.5707778930664062,
    "mean_activation": 0.10801356952783843,
    "L0": 584.4766063630692
  },
  {
    "global_step": 12600,
    "epoch": 39,
    "reconstruction_loss": 0.0008222093456424773,
    "l1_loss": 0.10575461387634277,
    "total_loss": 0.003994847647845745,
    "alive_count": 1024,
    "alive_frac": 1.0,
    "dead_count": 0,
    "mean_sparsity": 0.5706695318222046,
    "mean_activation": 0.10792197638507611,
    "L0": 584.3655685883037
  },
  {
    "global_step": 12700,
    "epoch": 40,
    "reconstruction_loss": 0.0008531432831659913,
    "l1_loss": 0.10753904283046722,
    "total_loss": 0.004079314414411783,
    "alive_count": 1024,
    "alive_frac": 1.0,
    "dead_count": 0,
    "mean_sparsity": 0.5686830878257751,
    "mean_activation": 0.10647156238555908,
    "L0": 582.3314453125
  },
  {
    "global_step": 12800,
    "epoch": 40,
    "reconstruction_loss": 0.0008193393587134778,
    "l1_loss": 0.10575193166732788,
    "total_loss": 0.003991897217929363,
    "alive_count": 1024,
    "alive_frac": 1.0,
    "dead_count": 0,
    "mean_sparsity": 0.5685552358627319,
    "mean_activation": 0.10637826919555664,
    "L0": 582.2005859375
  },
  {
    "global_step": 12900,
    "epoch": 40,
    "reconstruction_loss": 0.0008006957359611988,
    "l1_loss": 0.1063496544957161,
    "total_loss": 0.00399118522182107,
    "alive_count": 1024,
    "alive_frac": 1.0,
    "dead_count": 0,
    "mean_sparsity": 0.5685131549835205,
    "mean_activation": 0.10629619251598012,
    "L0": 582.1574928977273
  },
  {
    "global_step": 13000,
    "epoch": 41,
    "reconstruction_loss": 0.0008241890463978052,
    "l1_loss": 0.10707373917102814,
    "total_loss": 0.0040364013984799385,
    "alive_count": 1024,
    "alive_frac": 1.0,
    "dead_count": 0,
    "mean_sparsity": 0.5684583187103271,
    "mean_activation": 0.10616782677055817,
    "L0": 582.1013599452108
  },
  {
    "global_step": 13100,
    "epoch": 41,
    "reconstruction_loss": 0.0008234573761001229,
    "l1_loss": 0.1053743064403534,
    "total_loss": 0.003984686452895403,
    "alive_count": 1024,
    "alive_frac": 1.0,
    "dead_count": 0,
    "mean_sparsity": 0.5683702230453491,
    "mean_activation": 0.10608967959494449,
    "L0": 582.0111020043216
  },
  {
    "global_step": 13200,
    "epoch": 41,
    "reconstruction_loss": 0.0008171150693669915,
    "l1_loss": 0.1059984564781189,
    "total_loss": 0.003997068852186203,
    "alive_count": 1024,
    "alive_frac": 1.0,
    "dead_count": 0,
    "mean_sparsity": 0.568272054195404,
    "mean_activation": 0.10598953730878859,
    "L0": 581.9105950303832
  },
  {
    "global_step": 13300,
    "epoch": 41,
    "reconstruction_loss": 0.0008054710924625397,
    "l1_loss": 0.10539014637470245,
    "total_loss": 0.003967175260186195,
    "alive_count": 1024,
    "alive_frac": 1.0,
    "dead_count": 0,
    "mean_sparsity": 0.5681592226028442,
    "mean_activation": 0.10591246736415923,
    "L0": 581.7950153877201
  },
  {
    "global_step": 13400,
    "epoch": 42,
    "reconstruction_loss": 0.0007967387209646404,
    "l1_loss": 0.10342057794332504,
    "total_loss": 0.0038993561174720526,
    "alive_count": 1024,
    "alive_frac": 1.0,
    "dead_count": 0,
    "mean_sparsity": 0.5680208802223206,
    "mean_activation": 0.10581225783355795,
    "L0": 581.6534214416138
  },
  {
    "global_step": 13500,
    "epoch": 42,
    "reconstruction_loss": 0.0007903628284111619,
    "l1_loss": 0.10500514507293701,
    "total_loss": 0.003940517082810402,
    "alive_count": 1024,
    "alive_frac": 1.0,
    "dead_count": 0,
    "mean_sparsity": 0.5679388046264648,
    "mean_activation": 0.10574087147748741,
    "L0": 581.5693076864361
  },
  {
    "global_step": 13600,
    "epoch": 42,
    "reconstruction_loss": 0.0008016610518097878,
    "l1_loss": 0.1051780954003334,
    "total_loss": 0.003957003820687532,
    "alive_count": 1024,
    "alive_frac": 1.0,
    "dead_count": 0,
    "mean_sparsity": 0.5678371787071228,
    "mean_activation": 0.10566012994439154,
    "L0": 581.4653424937079
  },
  {
    "global_step": 13700,
    "epoch": 43,
    "reconstruction_loss": 0.0007818298181518912,
    "l1_loss": 0.10403872281312943,
    "total_loss": 0.0039029913023114204,
    "alive_count": 1024,
    "alive_frac": 1.0,
    "dead_count": 0,
    "mean_sparsity": 0.5677334666252136,
    "mean_activation": 0.10558282915218442,
    "L0": 581.3590522665194
  },
  {
    "global_step": 13800,
    "epoch": 43,
    "reconstruction_loss": 0.0007895756862126291,
    "l1_loss": 0.10456140339374542,
    "total_loss": 0.003926417790353298,
    "alive_count": 1024,
    "alive_frac": 1.0,
    "dead_count": 0,
    "mean_sparsity": 0.5676287412643433,
    "mean_activation": 0.10549373513173155,
    "L0": 581.2518793840651
  },
  {
    "global_step": 13900,
    "epoch": 43,
    "reconstruction_loss": 0.0007875457522459328,
    "l1_loss": 0.10578708350658417,
    "total_loss": 0.003961158450692892,
    "alive_count": 1024,
    "alive_frac": 1.0,
    "dead_count": 0,
    "mean_sparsity": 0.5675315260887146,
    "mean_activation": 0.10540926643905676,
    "L0": 581.1523484595849
  },
  {
    "global_step": 14000,
    "epoch": 44,
    "reconstruction_loss": 0.0007707749027758837,
    "l1_loss": 0.10446423292160034,
    "total_loss": 0.0039047019090503454,
    "alive_count": 1024,
    "alive_frac": 1.0,
    "dead_count": 0,
    "mean_sparsity": 0.5674363374710083,
    "mean_activation": 0.1053346012000759,
    "L0": 581.0548335072574
  },
  {
    "global_step": 14100,
    "epoch": 44,
    "reconstruction_loss": 0.0008154893293976784,
    "l1_loss": 0.10520326346158981,
    "total_loss": 0.003971586935222149,
    "alive_count": 1024,
    "alive_frac": 1.0,
    "dead_count": 0,
    "mean_sparsity": 0.5673331022262573,
    "mean_activation": 0.10525017299303964,
    "L0": 580.9491226523235
  },
  {
    "global_step": 14200,
    "epoch": 44,
    "reconstruction_loss": 0.0007610341999679804,
    "l1_loss": 0.10358896106481552,
    "total_loss": 0.003868703031912446,
    "alive_count": 1024,
    "alive_frac": 1.0,
    "dead_count": 0,
    "mean_sparsity": 0.5672399997711182,
    "mean_activation": 0.10516937057285232,
    "L0": 580.8538011695906
  },
  {
    "global_step": 14300,
    "epoch": 45,
    "reconstruction_loss": 0.0007844032952561975,
    "l1_loss": 0.10531120002269745,
    "total_loss": 0.003943738993257284,
    "alive_count": 1024,
    "alive_frac": 1.0,
    "dead_count": 0,
    "mean_sparsity": 0.5655831694602966,
    "mean_activation": 0.10382218360900879,
    "L0": 579.1571428571428
  },
  {
    "global_step": 14400,
    "epoch": 45,
    "reconstruction_loss": 0.0007642568671144545,
    "l1_loss": 0.10216086357831955,
    "total_loss": 0.0038290827069431543,
    "alive_count": 1024,
    "alive_frac": 1.0,
    "dead_count": 0,
    "mean_sparsity": 0.5654407739639282,
    "mean_activation": 0.10365212051956742,
    "L0": 579.0114004629629
  },
  {
    "global_step": 14500,
    "epoch": 45,
    "reconstruction_loss": 0.0007766919443383813,
    "l1_loss": 0.10397544503211975,
    "total_loss": 0.0038959551602602005,
    "alive_count": 1024,
    "alive_frac": 1.0,
    "dead_count": 0,
    "mean_sparsity": 0.5653294920921326,
    "mean_activation": 0.10357545081605303,
    "L0": 578.8974069148936
  },
  {
    "global_step": 14600,
    "epoch": 46,
    "reconstruction_loss": 0.000780075672082603,
    "l1_loss": 0.10467138886451721,
    "total_loss": 0.003920217044651508,
    "alive_count": 1024,
    "alive_frac": 1.0,
    "dead_count": 0,
    "mean_sparsity": 0.5652475357055664,
    "mean_activation": 0.10349777245920358,
    "L0": 578.8134286515279
  },
  {
    "global_step": 14700,
    "epoch": 46,
    "reconstruction_loss": 0.0007290391367860138,
    "l1_loss": 0.10171367973089218,
    "total_loss": 0.0037804495077580214,
    "alive_count": 1024,
    "alive_frac": 1.0,
    "dead_count": 0,
    "mean_sparsity": 0.5651004910469055,
    "mean_activation": 0.10337412143798108,
    "L0": 578.6629019495
  },
  {
    "global_step": 14800,
    "epoch": 46,
    "reconstruction_loss": 0.0007784172194078565,
    "l1_loss": 0.10373544692993164,
    "total_loss": 0.0038904803805053234,
    "alive_count": 1024,
    "alive_frac": 1.0,
    "dead_count": 0,
    "mean_sparsity": 0.5650025010108948,
    "mean_activation": 0.10329151415670136,
    "L0": 578.5625402023273
  },
  {
    "global_step": 14900,
    "epoch": 47,
    "reconstruction_loss": 0.0007796912686899304,
    "l1_loss": 0.10317084193229675,
    "total_loss": 0.0038748164661228657,
    "alive_count": 1024,
    "alive_frac": 1.0,
    "dead_count": 0,
    "mean_sparsity": 0.5649207234382629,
    "mean_activation": 0.1032156794278794,
    "L0": 578.4787989350162
  },
  {
    "global_step": 15000,
    "epoch": 47,
    "reconstruction_loss": 0.0007568402215838432,
    "l1_loss": 0.10248805582523346,
    "total_loss": 0.003831481793895364,
    "alive_count": 1024,
    "alive_frac": 1.0,
    "dead_count": 0,
    "mean_sparsity": 0.5647985935211182,
    "mean_activation": 0.10311416848210864,
    "L0": 578.353760327059
  },
  {
    "global_step": 15100,
    "epoch": 47,
    "reconstruction_loss": 0.0007845378713682294,
    "l1_loss": 0.10349845141172409,
    "total_loss": 0.0038894913159310818,
    "alive_count": 1024,
    "alive_frac": 1.0,
    "dead_count": 0,
    "mean_sparsity": 0.5646874904632568,
    "mean_activation": 0.10303852506488456,
    "L0": 578.240011993104
  },
  {
    "global_step": 15200,
    "epoch": 47,
    "reconstruction_loss": 0.0007619318785145879,
    "l1_loss": 0.10112151503562927,
    "total_loss": 0.0037955772131681442,
    "alive_count": 1024,
    "alive_frac": 1.0,
    "dead_count": 0,
    "mean_sparsity": 0.5645630359649658,
    "mean_activation": 0.10295421267663225,
    "L0": 578.112576132789
  },
  {
    "global_step": 15300,
    "epoch": 48,
    "reconstruction_loss": 0.0007750773802399635,
    "l1_loss": 0.10305774211883545,
    "total_loss": 0.0038668096531182528,
    "alive_count": 1024,
    "alive_frac": 1.0,
    "dead_count": 0,
    "mean_sparsity": 0.5644636154174805,
    "mean_activation": 0.10287949922307413,
    "L0": 578.0107068324108
  },
  {
    "global_step": 15400,
    "epoch": 48,
    "reconstruction_loss": 0.0007639551186002791,
    "l1_loss": 0.10284878313541412,
    "total_loss": 0.0038494186010211706,
    "alive_count": 1024,
    "alive_frac": 1.0,
    "dead_count": 0,
    "mean_sparsity": 0.5643452405929565,
    "mean_activation": 0.10279427808647933,
    "L0": 577.889529272261
  },
  {
    "global_step": 15500,
    "epoch": 48,
    "reconstruction_loss": 0.0007485706591978669,
    "l1_loss": 0.10154552012681961,
    "total_loss": 0.0037949359975755215,
    "alive_count": 1024,
    "alive_frac": 1.0,
    "dead_count": 0,
    "mean_sparsity": 0.5642274022102356,
    "mean_activation": 0.10270861164651066,
    "L0": 577.7688467678585
  },
  {
    "global_step": 15600,
    "epoch": 49,
    "reconstruction_loss": 0.0007509852293878794,
    "l1_loss": 0.10122128576040268,
    "total_loss": 0.003787623718380928,
    "alive_count": 1024,
    "alive_frac": 1.0,
    "dead_count": 0,
    "mean_sparsity": 0.5641009211540222,
    "mean_activation": 0.1026134428348654,
    "L0": 577.6392927492731
  },
  {
    "global_step": 15700,
    "epoch": 49,
    "reconstruction_loss": 0.0007500463398173451,
    "l1_loss": 0.10203322768211365,
    "total_loss": 0.003811043221503496,
    "alive_count": 1024,
    "alive_frac": 1.0,
    "dead_count": 0,
    "mean_sparsity": 0.5639795064926147,
    "mean_activation": 0.1025373370492867,
    "L0": 577.515094668877
  },
  {
    "global_step": 15800,
    "epoch": 49,
    "reconstruction_loss": 0.0007435174193233252,
    "l1_loss": 0.10197024047374725,
    "total_loss": 0.0038026245310902596,
    "alive_count": 1024,
    "alive_frac": 1.0,
    "dead_count": 0,
    "mean_sparsity": 0.5638736486434937,
    "mean_activation": 0.10245587030268738,
    "L0": 577.4066552483484
  }
]