{
  "delta_full": -0.31666666666666665,
  "delta_full_ci": {
    "mean": -0.31666666666666665,
    "ci_lower": -0.37333333333333335,
    "ci_upper": -0.26,
    "std": 0.4997221450188316,
    "n": 300
  },
  "baseline_mean": 0.9233333333333333,
  "curves": {
    "pca_top": {
      "1": {
        "mean": -0.023333333333333334,
        "ci_lower": -0.05333333333333334,
        "ci_upper": 0.0033333333333333335,
        "std": 0.2505771116620369,
        "n": 300
      },
      "2": {
        "mean": -0.16333333333333333,
        "ci_lower": -0.21008333333333326,
        "ci_upper": -0.11666666666666667,
        "std": 0.42816144410983836,
        "n": 300
      },
      "4": {
        "mean": -0.15333333333333332,
        "ci_lower": -0.2,
        "ci_upper": -0.10666666666666667,
        "std": 0.4279667692187742,
        "n": 300
      },
      "8": {
        "mean": -0.14,
        "ci_lower": -0.1834166666666666,
        "ci_upper": -0.09666666666666666,
        "std": 0.4087378948258488,
        "n": 300
      },
      "16": {
        "mean": -0.14333333333333334,
        "ci_lower": -0.19,
        "ci_upper": -0.09991666666666675,
        "std": 0.4034710508684469,
        "n": 300
      },
      "32": {
        "mean": -0.24666666666666667,
        "ci_lower": -0.3,
        "ci_upper": -0.19333333333333333,
        "std": 0.468140529708287,
        "n": 300
      },
      "64": {
        "mean": -0.28,
        "ci_lower": -0.33666666666666667,
        "ci_upper": -0.22666666666666666,
        "std": 0.48469921944782757,
        "n": 300
      },
      "128": {
        "mean": -0.31,
        "ci_lower": -0.36666666666666664,
        "ci_upper": -0.25333333333333335,
        "std": 0.49722563623905525,
        "n": 300
      },
      "256": {
        "mean": -0.3233333333333333,
        "ci_lower": -0.38,
        "ci_upper": -0.2633333333333333,
        "std": 0.5021177374104825,
        "n": 300
      },
      "512": {
        "mean": -0.31666666666666665,
        "ci_lower": -0.37,
        "ci_upper": -0.26,
        "std": 0.4997221450188316,
        "n": 300
      }
    },
    "pca_bottom": {
      "1": {
        "mean": 0.0033333333333333335,
        "ci_lower": 0.0,
        "ci_upper": 0.01,
        "std": 0.057638721552635275,
        "n": 300
      },
      "2": {
        "mean": 0.0,
        "ci_lower": -0.01,
        "ci_upper": 0.01,
        "std": 0.08164965809277261,
        "n": 300
      },
      "4": {
        "mean": 0.0033333333333333335,
        "ci_lower": 0.0,
        "ci_upper": 0.01,
        "std": 0.057638721552635275,
        "n": 300
      },
      "8": {
        "mean": 0.0,
        "ci_lower": -0.01,
        "ci_upper": 0.01,
        "std": 0.08164965809277261,
        "n": 300
      },
      "16": {
        "mean": 0.0033333333333333335,
        "ci_lower": 0.0,
        "ci_upper": 0.01,
        "std": 0.057638721552635275,
        "n": 300
      },
      "32": {
        "mean": 0.0033333333333333335,
        "ci_lower": 0.0,
        "ci_upper": 0.01,
        "std": 0.057638721552635275,
        "n": 300
      },
      "64": {
        "mean": 0.0033333333333333335,
        "ci_lower": 0.0,
        "ci_upper": 0.01,
        "std": 0.057638721552635275,
        "n": 300
      },
      "128": {
        "mean": 0.0033333333333333335,
        "ci_lower": -0.006666666666666667,
        "ci_upper": 0.013333333333333334,
        "std": 0.09994442900376634,
        "n": 300
      },
      "256": {
        "mean": 0.006666666666666667,
        "ci_lower": -0.006666666666666667,
        "ci_upper": 0.02,
        "std": 0.11527744310527054,
        "n": 300
      },
      "512": {
        "mean": -0.32,
        "ci_lower": -0.3734166666666666,
        "ci_upper": -0.2633333333333333,
        "std": 0.500932463844512,
        "n": 300
      }
    },
    "random": {
      "1": {
        "mean": 0.002666666666666667,
        "ci_lower": -0.005333333333333333,
        "ci_upper": 0.011333333333333334,
        "std": 0.005333333333333333,
        "n": 5
      },
      "2": {
        "mean": 0.002666666666666667,
        "ci_lower": -0.006,
        "ci_upper": 0.012,
        "std": 0.0038873012632302003,
        "n": 5
      },
      "4": {
        "mean": 0.008,
        "ci_lower": 1.7347234759768072e-19,
        "ci_upper": 0.018000000000000002,
        "std": 0.006863753427324666,
        "n": 5
      },
      "8": {
        "mean": 0.006,
        "ci_lower": -0.004666666666666667,
        "ci_upper": 0.018,
        "std": 0.004898979485566357,
        "n": 5
      },
      "16": {
        "mean": 0.008,
        "ci_lower": -0.003333333333333333,
        "ci_upper": 0.021333333333333333,
        "std": 0.001632993161855452,
        "n": 5
      },
      "32": {
        "mean": 0.01,
        "ci_lower": -0.008,
        "ci_upper": 0.02934999999999998,
        "std": 0.009189365834726815,
        "n": 5
      },
      "64": {
        "mean": 0.009333333333333332,
        "ci_lower": -0.008,
        "ci_upper": 0.028666666666666667,
        "std": 0.005734883511361751,
        "n": 5
      },
      "128": {
        "mean": -8.673617379884036e-20,
        "ci_lower": -0.02401666666666665,
        "ci_upper": 0.02268333333333332,
        "std": 0.005577733510227171,
        "n": 5
      },
      "256": {
        "mean": -0.07533333333333334,
        "ci_lower": -0.11266666666666666,
        "ci_upper": -0.03933333333333333,
        "std": 0.025525586292102193,
        "n": 5
      },
      "512": {
        "mean": -0.31933333333333336,
        "ci_lower": -0.37534999999999996,
        "ci_upper": -0.26266666666666666,
        "std": 0.0024944382578492926,
        "n": 5
      }
    },
    "probe_sae": {
      "1": {
        "mean": 0.006666666666666667,
        "ci_lower": 0.0,
        "ci_upper": 0.016666666666666666,
        "std": 0.08137703743822469,
        "n": 300
      },
      "2": {
        "mean": 0.0,
        "ci_lower": 0.0,
        "ci_upper": 0.0,
        "std": 0.0,
        "n": 300
      },
      "4": {
        "mean": 0.0,
        "ci_lower": -0.01,
        "ci_upper": 0.01,
        "std": 0.08164965809277261,
        "n": 300
      },
      "5": {
        "mean": 0.006666666666666667,
        "ci_lower": -0.006666666666666667,
        "ci_upper": 0.02,
        "std": 0.11527744310527054,
        "n": 300
      }
    }
  },
  "r_star": {
    "half": {
      "pca_top": 2,
      "pca_bottom": 512,
      "random": 512,
      "probe_sae": 5
    },
    "ninety": {
      "pca_top": 128,
      "pca_bottom": 512,
      "random": 512,
      "probe_sae": 5
    }
  },
  "alignment": {
    "r_star": 128,
    "probe_sae_energy": 0.2637507915496826,
    "principal_angles_cos": [
      0.5475098490715027,
      0.5361589193344116,
      0.5314556956291199,
      0.4906294345855713,
      0.45646312832832336
    ],
    "random_control_energy_mean": 0.2505320072174072,
    "random_control_energy_std": 0.0025263534743875157
  },
  "min_causal_rank": 128,
  "subspace_linearity": 0.45304401799540794,
  "meta": {
    "task": "maze",
    "checkpoint": "/home/leo.rodrigues/HRM/checkpoints/sapientinc-hrm-maze-30x30-hard/checkpoint",
    "num_puzzles": 300,
    "n_pca": 300,
    "ranks": [
      1,
      2,
      4,
      8,
      16,
      32,
      64,
      128,
      256,
      512
    ],
    "n_random_bases": 5,
    "max_steps": 16,
    "seed": 42,
    "elapsed_s": 3477.9
  }
}